tabular_nn
